genice2_dev.py
genice2_dev-0.1.1.dist-info/METADATA
genice2_dev-0.1.1.dist-info/WHEEL
genice2_dev-0.1.1.dist-info/top_level.txt
genice2_dev-0.1.1.dist-info/RECORD
