Metadata-Version: 2.1
Name: genice2-dev
Version: 0.1.1
Summary: Library to develop GenIce2 plugins.
Home-page: https://github.com/vitroid/genice-dev/
Author: Masakazu Matsumoto
Author-email: vitroid@gmail.com
License: MIT
Keywords: genice,CIF
Platform: UNKNOWN
Classifier: Development Status :: 4 - Beta
Classifier: Intended Audience :: Developers
Classifier: Programming Language :: Python
Classifier: Programming Language :: Python :: 3.6
Requires-Dist: jinja2
